django_pat/__init__.py
django_pat/admin.py
django_pat/apps.py
django_pat/http.py
django_pat/middleware.py
django_pat/migrations/0001_initial.py
django_pat/migrations/__init__.py
django_pat/models.py
django_pat/rest_framework/__init__.py
django_pat/rest_framework/auth.py
django_pat/rest_framework/urls.py
django_pat/rest_framework/views.py
django_pat/templates/personal_access_token/confirm_delete.html
django_pat/templates/personal_access_token/create.html
django_pat/templates/personal_access_token/list.html
django_pat/urls.py
django_pat/views.py
django_pat-2.0.0.dist-info/WHEEL
django_pat-2.0.0.dist-info/METADATA
django_pat-2.0.0.dist-info/LICENSE
django_pat-2.0.0.dist-info/RECORD
