Metadata-Version: 2.1
Name: django-pat
Version: 2.0.0
Summary: A Django package for creating, using, and managing personal access tokens.
License: MIT
Author: Chris Muthig
Author-email: camuthig@gmail.com
Requires-Python: >=3.8,<3.13
Classifier: Framework :: Django :: 4.0
Classifier: Framework :: Django :: 4.1
Classifier: Framework :: Django :: 4.2
Classifier: Framework :: Django :: 5.0
Classifier: Framework :: Django :: 5.1
Classifier: Framework :: Django :: 5.2
Classifier: License :: OSI Approved :: MIT License
Classifier: Programming Language :: Python :: 3
Classifier: Programming Language :: Python :: 3.8
Classifier: Programming Language :: Python :: 3.9
Classifier: Programming Language :: Python :: 3.10
Classifier: Programming Language :: Python :: 3.11
Provides-Extra: djangorestframework
Requires-Dist: django (>=4.0,<4.3) ; python_version >= "3.8" and python_version < "3.10"
Requires-Dist: django (>=4.0,<6.0) ; python_version >= "3.10" and python_version < "3.11"
Requires-Dist: django (>=4.1,<6.0) ; python_version >= "3.11" and python_version < "3.12"
Requires-Dist: django (>=4.2,<6.0) ; python_version >= "3.12" and python_version < "3.13"
Requires-Dist: django (>=5.1,<6.0) ; python_version >= "3.13" and python_version < "3.14"
Requires-Dist: djangorestframework (>=3.15,<4.0) ; extra == "djangorestframework"
